{
  "schema_version": 2,
  "law_number": "150-ФЗ",
  "law_date": "13.12.1996",
  "article_number": "23",
  "title": "Государственная пошлина, взимаемая за юридически значимые действия в сфере оборота оружия",
  "heading": "Статья 23. Государственная пошлина, взимаемая за юридически значимые действия в сфере оборота оружия",
  "revision_date": "04.07.2026",
  "source_type": "public_legal_system",
  "source_name": "КонсультантПлюс",
  "source_url": "https://www.consultant.ru/document/cons_doc_LAW_12679/4b70c00e85160308fd5a9d5580f07c5e8b6b88d3/",
  "fetched_at": "2026-07-20T21:55:45+00:00",
  "source_sha256": "c0d9c08b3e9022941659d55238bb89bae7c17fb7eb4e1c83734dd333ba337813",
  "clean_sha256": "2f7c61d0413d63c2b40dbd781c7b6cf701d7129f70bb3f53e59ce646ce9dff47",
  "source_text": "Статья 23. Государственная пошлина, взимаемая за юридически значимые действия в сфере оборота оружия\n\n(в ред. Федерального закона от 01.07.2017 N 151-ФЗ)\n\n(см. текст в предыдущей редакции )\n\nФедеральным органом исполнительной власти, уполномоченным в сфере оборота оружия, за совершение юридически значимых действий в сфере оборота оружия взимается государственная пошлина в порядке, установленном законодательством Российской Федерации о налогах и сборах.\n\nФедеральным органом исполнительной власти, осуществляющим функции по выработке и реализации государственной политики и нормативно-правовому регулированию в сфере внутренних дел, за совершение юридически значимых действий в сфере оборота оружия взимается государственная пошлина в порядке, установленном законодательством Российской Федерации о налогах и сборах.\n\n(часть вторая введена Федеральным законом от 31.07.2025 N 270-ФЗ)\n\nСтатья 22. Хранение гражданского и служебного оружия и патронов к нему\nСтатья 24. Применение оружия гражданами Российской Федерации",
  "clean_text": "(см. текст в предыдущей редакции )\n\nФедеральным органом исполнительной власти, уполномоченным в сфере оборота оружия, за совершение юридически значимых действий в сфере оборота оружия взимается государственная пошлина в порядке, установленном законодательством Российской Федерации о налогах и сборах.\n\nФедеральным органом исполнительной власти, осуществляющим функции по выработке и реализации государственной политики и нормативно-правовому регулированию в сфере внутренних дел, за совершение юридически значимых действий в сфере оборота оружия взимается государственная пошлина в порядке, установленном законодательством Российской Федерации о налогах и сборах.\n\nСтатья 22. Хранение гражданского и служебного оружия и патронов к нему\nСтатья 24. Применение оружия гражданами Российской Федерации"
}
